classicdata/__init__.py
classicdata/dataset.py
classicdata/files.py
classicdata/info.py
classicdata/settings.py
classicdata/utility.py
classicdata/datasets/__init__.py
classicdata/datasets/ionosphere.py
classicdata/datasets/letterrecognition.py
classicdata/datasets/magic.py
classicdata/datasets/pendigits.py
classicdata/datasets/robnav.py
classicdata/datasets/segmentation.py
classicdata/datasets/usps.py
classicdata-0.1.0a2.dist-info/LICENSE
classicdata-0.1.0a2.dist-info/METADATA
classicdata-0.1.0a2.dist-info/WHEEL
classicdata-0.1.0a2.dist-info/top_level.txt
classicdata-0.1.0a2.dist-info/RECORD
